chinese_herbal_sentiment/__init__.py
chinese_herbal_sentiment/core/__init__.py
chinese_herbal_sentiment/core/bert_sentiment_analysis.py
chinese_herbal_sentiment/core/deep_learning_sentiment.py
chinese_herbal_sentiment/core/keyword_extraction.py
chinese_herbal_sentiment/core/sentiment_analysis.py
chinese_herbal_sentiment/core/textcnn_sentiment_analysis.py
chinese_herbal_sentiment/core/textrank_sentiment_analysis.py
chinese_herbal_sentiment/models/bert_sentiment_model/config.json
chinese_herbal_sentiment/models/bert_sentiment_model/special_tokens_map.json
chinese_herbal_sentiment/models/bert_sentiment_model/tokenizer_config.json
chinese_herbal_sentiment/models/bert_sentiment_model/vocab.txt
chinese_herbal_sentiment/utils/__init__.py
chinese_herbal_sentiment/utils/data_analysis.py
chinese_herbal_sentiment/utils/generate_all_figures_chinese.py
chinese_herbal_sentiment/utils/generate_all_figures_unified.py
chinese_herbal_sentiment/utils/generate_bert_real_training.py
chinese_herbal_sentiment/utils/generate_lstm_architecture.py
chinese_herbal_sentiment/utils/generate_radar_chart.py
chinese_herbal_sentiment/utils/generate_regression_analysis_figure.py
chinese_herbal_sentiment/utils/generate_training_figures.py
chinese_herbal_sentiment/utils/keyword_mapping.py
chinese_herbal_sentiment/utils/read_comments.py
chinese_herbal_sentiment/utils/scholar_search.py
chinese_herbal_sentiment/utils/unified_color_scheme.py
chinese_herbal_sentiment/utils/update_training_figures_unified.py
chinese_herbal_sentiment-0.1.0.dist-info/licenses/LICENSE
chinese_herbal_sentiment-0.1.0.dist-info/METADATA
chinese_herbal_sentiment-0.1.0.dist-info/WHEEL
chinese_herbal_sentiment-0.1.0.dist-info/entry_points.txt
chinese_herbal_sentiment-0.1.0.dist-info/top_level.txt
chinese_herbal_sentiment-0.1.0.dist-info/RECORD
