Metadata-Version: 2.4
Name: chinese-herbal-sentiment
Version: 0.1.0
Summary: Chinese Herbal Medicine E-commerce Sentiment Analysis System
Home-page: https://github.com/chenxingqiang/chinese-herbal-sentiment
Author: Luo Chengwen, Chen Xingqiang
Author-email: Luo Chengwen <luochengwen@turingai.cc>, Chen Xingqiang <chenxingqiang@turingai.cc>
Maintainer-email: Luo Chengwen <luochengwen@turingai.cc>, Chen Xingqiang <chenxingqiang@turingai.cc>
License: MIT
Project-URL: Homepage, https://github.com/chenxingqiang/chinese-herbal-sentiment
Project-URL: Documentation, https://github.com/chenxingqiang/chinese-herbal-sentiment#readme
Project-URL: Repository, https://github.com/chenxingqiang/chinese-herbal-sentiment
Project-URL: Bug Tracker, https://github.com/chenxingqiang/chinese-herbal-sentiment/issues
Keywords: sentiment-analysis,chinese-herbal-medicine,e-commerce,nlp,machine-learning,deep-learning,bert,textcnn,textrank,supply-chain,quality-evaluation
Classifier: Development Status :: 3 - Alpha
Classifier: Intended Audience :: Science/Research
Classifier: License :: OSI Approved :: MIT License
Classifier: Programming Language :: Python :: 3
Classifier: Programming Language :: Python :: 3.8
Classifier: Programming Language :: Python :: 3.9
Classifier: Programming Language :: Python :: 3.10
Classifier: Programming Language :: Python :: 3.11
Classifier: Programming Language :: Python :: 3.12
Classifier: Topic :: Scientific/Engineering :: Artificial Intelligence
Classifier: Topic :: Text Processing :: Linguistic
Classifier: Topic :: Software Development :: Libraries :: Python Modules
Requires-Python: >=3.8
License-File: LICENSE
Requires-Dist: pandas>=1.3.0
Requires-Dist: numpy>=1.21.0
Requires-Dist: scikit-learn>=1.0.0
Requires-Dist: jieba>=0.42.1
Requires-Dist: matplotlib>=3.5.0
Requires-Dist: seaborn>=0.11.0
Requires-Dist: wordcloud>=1.8.0
Requires-Dist: networkx>=2.6.0
Requires-Dist: openpyxl>=3.0.0
Requires-Dist: tqdm>=4.62.0
Requires-Dist: gensim>=4.0.0
Requires-Dist: xlrd>=2.0.0
Provides-Extra: deep-learning
Requires-Dist: torch>=1.9.0; extra == "deep-learning"
Requires-Dist: tensorflow>=2.6.0; extra == "deep-learning"
Requires-Dist: transformers>=4.11.0; extra == "deep-learning"
Requires-Dist: keras>=2.6.0; extra == "deep-learning"
Provides-Extra: dev
Requires-Dist: pytest>=6.0.0; extra == "dev"
Requires-Dist: pytest-cov>=2.12.0; extra == "dev"
Requires-Dist: black>=21.0.0; extra == "dev"
Requires-Dist: flake8>=3.9.0; extra == "dev"
Requires-Dist: mypy>=0.910; extra == "dev"
Requires-Dist: sphinx>=4.0.0; extra == "dev"
Requires-Dist: sphinx-rtd-theme>=1.0.0; extra == "dev"
Provides-Extra: all
Requires-Dist: torch>=1.9.0; extra == "all"
Requires-Dist: tensorflow>=2.6.0; extra == "all"
Requires-Dist: transformers>=4.11.0; extra == "all"
Requires-Dist: keras>=2.6.0; extra == "all"
Requires-Dist: pytest>=6.0.0; extra == "all"
Requires-Dist: pytest-cov>=2.12.0; extra == "all"
Requires-Dist: black>=21.0.0; extra == "all"
Requires-Dist: flake8>=3.9.0; extra == "all"
Requires-Dist: mypy>=0.910; extra == "all"
Requires-Dist: sphinx>=4.0.0; extra == "all"
Requires-Dist: sphinx-rtd-theme>=1.0.0; extra == "all"
Dynamic: author
Dynamic: home-page
Dynamic: license-file
Dynamic: requires-python
